<?xml version="1.0" encoding="utf-8"?>
<resources>
  <style name="AppTheme" parent="@style/AppTheme.Base"/>

  <style name="AppTheme.Base" parent="android:Theme.Holo.NoActionBar">
    <item name="android:colorPrimary">@color/theme_primary</item>
    <item name="android:colorPrimaryDark">@color/theme_primary</item>
    <item name="android:colorAccent">@color/theme_secondary</item>
    <item name="android:windowNoTitle">true</item>
    <item name="android:windowActionBar">false</item>
  </style>

  <style name="PrimaryButtonTheme" parent="@style/AppTheme.Base">
    <item name="android:colorAccent">@color/theme_primary</item>
  </style>
</resources>
